Workbook

Sheet Dashboard
A1: Sales Performance Analysis Dashboard
A2: Total Sales | G2: Total Orders | M2: Total Profit | S2: Average Sales
A3: =Analysis!B3 -> 2686559 | G3: =Analysis!B5 -> 110 | M3: =Analysis!B4 -> 649459 | S3: =Analysis!B6 -> 24423.264
A4: Profit Margin % | G4: Average Order Value | S4: Highest Selling Category
A5: =((M3 / A3 )/ 100)*100 -> 0.24174381 | G5: =A3/G3 -> 24423.264 | S5: =S7 -> Laptop
A6: Sales by Age | S6: Top 10 Selling Items
S7: =Sales!E4 -> Laptop | V7: =Sales!F4 -> 882000
A8: 18-25 | C8: =Cleaned_Data!X2 -> 13 | S8: =Sales!E5 -> Smartphone | V8: =Sales!F5 -> 584500
S9: =Sales!E6 -> Tablet | V9: =Sales!F6 -> 265150
A10: 26-35 | C10: =Cleaned_Data!X3 -> 35 | S10: =Sales!E7 -> Table | V10: =Sales!F7 -> 141880
S11: =Sales!E8 -> Smartwatch | V11: =Sales!F8 -> 117200
A12: 36-45 | C12: =Cleaned_Data!X4 -> 23 | S12: =Sales!E9 -> Monitor | V12: =Sales!F9 -> 91800
S13: =Sales!E10 -> Chair | V13: =Sales!F10 -> 86575
A14: 46+ | C14: =Cleaned_Data!X5 -> 39 | S14: =Sales!E11 -> Headphones | V14: =Sales!F11 -> 76250
S15: =Sales!E12 -> Shoes | V15: =Sales!F12 -> 73615
S16: =Sales!E13 -> Perfume | V16: =Sales!F13 -> 73115
J30: v

Sheet Raw_Data
A1: Order_ID | B1: Order_Date | C1: Customer_ID | D1: Customer_Name | E1: Age | F1: Gender | G1: City | H1: State | I1: Customer_Type | J1: Product_ID | K1: Category | L1: Product_Name | M1: Quantity | N1: Unit_Price | O1: Discount | P1: Payment_Method | Q1: Delivery_Status | R1: Sales_Amount | S1: Cost | T1: Profit
A2: ORD001 | B2: 45658 | C2: C101 | D2: Rahul | E2: 25 | F2: Male | G2: Hyderabad | H2: Telangana | I2: New | J2: P101 | K2: Electronics | L2: Laptop | M2: 1 | N2: 60000 | O2: 5 | P2: UPI | Q2: Delivered | R2: 57000 | S2: 45000 | T2: 12000
A3: ORD002 | B3: 45660 | C3: C102 | D3: Anu | E3: 32 | F3: Female | G3: Vijayawada | H3: Andhra Pradesh | I3: Returning | J3: P102 | K3: Furniture | L3: Chair | M3: 4 | N3: 3000 | O3: 10 | P3: Card | Q3: Delivered | R3: 10800 | S3: 7000 | T3: 3800
A4: ORD003 | B4: 45662 | C4: C103 | D4: Kiran | E4: 28 | F4: Male | G4: Chennai | H4: Tamil Nadu | I4: New | J4: P103 | K4: Mobile | L4: Smartphone | M4: 2 | N4: 25000 | O4: 8 | P4: UPI | Q4: Delivered | R4: 46000 | S4: 36000 | T4: 10000
A5: ORD004 | B5: 45665 | C5: C104 | D5: Priya | E5: 35 | F5: Female | G5: Bangalore | H5: Karnataka | I5: Returning | J5: P104 | K5: Clothing | L5: Shirt | M5: 5 | N5: 1500 | O5: 5 | P5: Cash | Q5: Pending | R5: 7125 | S5: 5000 | T5: 2125
A6: ORD005 | B6: 45669 | C6: C105 | D6: Arjun | E6: 40 | F6: Male | G6: Mumbai | H6: Maharashtra | I6: New | J6: P105 | K6: Electronics | L6: Tablet | M6: 1 | N6: 30000 | O6: 12 | P6: Card | Q6: Delivered | R6: 26400 | S6: 21000 | T6: 5400
A7: ORD006 | B7: 45672 | C7: C106 | D7: Sneha | E7: 27 | F7: Female | G7: Delhi | H7: Delhi | I7: Returning | J7: P106 | K7: Beauty | L7: Skincare | M7: 3 | N7: 2000 | O7: 10 | P7: UPI | Q7: Delivered | R7: 5400 | S7: 3500 | T7: 1900
A8: ORD007 | B8: 45675 | C8: C107 | D8: Vinay | E8: 30 | F8: Male | G8: Pune | H8: Maharashtra | I8: New | J8: P107 | K8: Furniture | L8: Table | M8: 2 | N8: 8000 | O8: 7 | P8: Card | Q8: Delivered | R8: 14880 | S8: 11000 | T8: 3880
A9: ORD008 | B9: 45679 | C9: C108 | D9: Divya | E9: 26 | F9: Female | G9: Hyderabad | H9: Telangana | I9: New | J9: P108 | K9: Mobile | L9: Headphones | M9: 3 | N9: 4000 | O9: 5 | P9: UPI | Q9: Cancelled | R9: 11400 | S9: 8000 | T9: 3400
A10: ORD009 | B10: 45682 | C10: C109 | D10: Ravi | E10: 45 | F10: Male | G10: Chennai | H10: Tamil Nadu | I10: Returning | J10: P109 | K10: Electronics | L10: Monitor | M10: 2 | N10: 12000 | O10: 10 | P10: Card | Q10: Delivered | R10: 21600 | S10: 16000 | T10: 5600
A11: ORD010 | B11: 45685 | C11: C110 | D11: Latha | E11: 38 | F11: Female | G11: Vijayawada | H11: Andhra Pradesh | I11: New | J11: P110 | K11: Clothing | L11: Shoes | M11: 2 | N11: 5000 | O11: 15 | P11: Cash | Q11: Delivered | R11: 8500 | S11: 6000 | T11: 2500
A12: ORD011 | B12: 45729 | C12: C125 | D12: Manish | E12: 33 | F12: Male | G12: Bangalore | H12: Karnataka | I12: New | J12: P148 | K12: Electronics | L12: Laptop | M12: 4 | N12: 55000 | O12: 0 | P12: UPI | Q12: Delivered | R12: 220000 | S12: 168000 | T12: 52000
A13: ORD012 | B13: 45702 | C13: C140 | D13: Vijay | E13: 30 | F13: Male | G13: Kochi | H13: Kerala | I13: Returning | J13: P148 | K13: Furniture | L13: Desk Lamp | M13: 3 | N13: 1500 | O13: 0 | P13: Card | Q13: Pending | R13: 4500 | S13: 2700 | T13: 1800
... A111: ORD110 | B111: 45698 | C111: C192 | D111: Rohan | E111: 51 | F111: Male | G111: Bangalore | H111: Karnataka | I111: Returning | J111: P132 | K111: Clothing | L111: Jacket | M111: 2 | N111: 4000 | O111: 10 | P111: Cash | Q111: Delivered | R111: 7200 | S111: 5200 | T111: 2000

Sheet Sales
A3: Row Labels | B3: Sum of Sales_Amount | C3: Sum of Profit
A4: Chair | B4: 86575 | C4: 28975 | E4: Laptop | F4: 882000 | G4: 165000
A5: Charger | B5: 21970 | C5: 9970 | E5: Smartphone | F5: 584500 | G5: 130500
A6: Desk Lamp | B6: 13725 | C6: 4725 | E6: Tablet | F6: 265150 | G6: 64150
A7: Hair Dryer | B7: 15000 | C7: 4600 | E7: Table | F7: 141880 | G7: 39880
A8: Headphones | B8: 76250 | C8: 23450 | E8: Smartwatch | F8: 117200 | G8: 29200
A9: Jacket | B9: 45840 | C9: 14640 | E9: Monitor | F9: 91800 | G9: 20800
A10: Jeans | B10: 22250 | C10: 7250 | E10: Chair | F10: 86575 | G10: 28975
A11: Laptop | B11: 882000 | C11: 165000 | E11: Headphones | F11: 76250 | G11: 23450
A12: Makeup Kit | B12: 34125 | C12: 10125 | E12: Shoes | F12: 73615 | G12: 22815
A13: Monitor | B13: 91800 | C13: 20800 | E13: Perfume | F13: 73115 | G13: 27115
A14: Perfume | B14: 73115 | C14: 27115 | E14: Shirt | F14: 57129 | G14: 21129
A15: Power Bank | B15: 37580 | C15: 12380 | E15: Jacket | F15: 45840 | G15: 14640
... A23: Tablet | B23: 265150 | C23: 64150 | E23: Desk Lamp | F23: 13725 | G23: 4725
A24: Grand Total | B24: 2686559 | C24: 649459

Sheet State
A3: Row Labels | B3: Sum of Sales_Amount | D3: State | E3: Sales
A4: Andhra Pradesh | B4: 598705 | D4: Andhra Pradesh | E4: 598705
A5: Delhi | B5: 95400 | D5: Delhi | E5: 95400
A6: Gujarat | B6: 45570 | D6: Gujarat | E6: 45570
A7: Karnataka | B7: 333086 | D7: Karnataka | E7: 333086
A8: Kerala | B8: 192492 | D8: Kerala | E8: 192492
A9: Maharashtra | B9: 284790 | D9: Maharashtra | E9: 284790
A10: Rajasthan | B10: 465180 | D10: Rajasthan | E10: 465180
A11: Tamil Nadu | B11: 243510 | D11: Tamil Nadu | E11: 243510
A12: Telangana | B12: 89196 | D12: Telangana | E12: 89196
A13: Uttar Pradesh | B13: 187480 | D13: Uttar Pradesh | E13: 187480
A14: West Bengal | B14: 151150 | D14: West Bengal | E14: 151150
A15: Grand Total | B15: 2686559

Sheet Cleaned_Data
A1: Order_ID | B1: Order_Date | C1: Customer_ID | D1: Customer_Name | E1: Age | F1: Gender | G1: City | H1: State | I1: Customer_Type | J1: Product_ID | K1: Category | L1: Product_Name | M1: Quantity | N1: Unit_Price | O1: Discount | P1: Payment_Method | Q1: Delivery_Status | R1: Sales_Amount | S1: Cost | T1: Profit
A2: ORD001 | B2: 45658 | C2: C101 | D2: Rahul | E2: 25 | F2: Male | G2: Hyderabad | H2: Telangana | I2: New | J2: P101 | K2: Electronics | L2: Laptop | M2: 1 | N2: 60000 | O2: 5 | P2: UPI | Q2: Delivered | R2: 57000 | S2: 45000 | T2: 12000 | V2: =IF(E2<=25,"18-25", IF(E2<=35,"26-35", IF(E2<=45,"36-45","46+"))) -> 18-25 | X2: =COUNTIF(V:V,"18-25") -> 13
A3: ORD002 | B3: 45660 | C3: C102 | D3: Anu | E3: 32 | F3: Female | G3: Vijayawada | H3: Andhra Pradesh | I3: Returning | J3: P102 | K3: Furniture | L3: Chair | M3: 4 | N3: 3000 | O3: 10 | P3: Card | Q3: Delivered | R3: 10800 | S3: 7000 | T3: 3800 | V3: =IF(E3<=25,"18-25", IF(E3<=35,"26-35", IF(E3<=45,"36-45","46+"))) -> 26-35 | X3: =COUNTIF(V:V,"26-35") -> 35
A4: ORD003 | B4: 45662 | C4: C103 | D4: Kiran | E4: 28 | F4: Male | G4: Chennai | H4: Tamil Nadu | I4: New | J4: P103 | K4: Mobile | L4: Smartphone | M4: 2 | N4: 25000 | O4: 8 | P4: UPI | Q4: Delivered | R4: 46000 | S4: 36000 | T4: 10000 | V4: =IF(E4<=25,"18-25", IF(E4<=35,"26-35", IF(E4<=45,"36-45","46+"))) -> 26-35 | X4: =COUNTIF(V:V,"36-45") -> 23
A5: ORD004 | B5: 45665 | C5: C104 | D5: Priya | E5: 35 | F5: Female | G5: Bangalore | H5: Karnataka | I5: Returning | J5: P104 | K5: Clothing | L5: Shirt | M5: 5 | N5: 1500 | O5: 5 | P5: Cash | Q5: Pending | R5: 7125 | S5: 5000 | T5: 2125 | V5: =IF(E5<=25,"18-25", IF(E5<=35,"26-35", IF(E5<=45,"36-45","46+"))) -> 26-35 | X5: =COUNTIF(V:V,"46+") -> 39
A6: ORD005 | B6: 45669 | C6: C105 | D6: Arjun | E6: 40 | F6: Male | G6: Mumbai | H6: Maharashtra | I6: New | J6: P105 | K6: Electronics | L6: Tablet | M6: 1 | N6: 30000 | O6: 12 | P6: Card | Q6: Delivered | R6: 26400 | S6: 21000 | T6: 5400 | V6: =IF(E6<=25,"18-25", IF(E6<=35,"26-35", IF(E6<=45,"36-45","46+"))) -> 36-45
A7: ORD006 | B7: 45672 | C7: C106 | D7: Sneha | E7: 27 | F7: Female | G7: Delhi | H7: Delhi | I7: Returning | J7: P106 | K7: Beauty | L7: Skincare | M7: 3 | N7: 2000 | O7: 10 | P7: UPI | Q7: Delivered | R7: 5400 | S7: 3500 | T7: 1900 | V7: =IF(E7<=25,"18-25", IF(E7<=35,"26-35", IF(E7<=45,"36-45","46+"))) -> 26-35
A8: ORD007 | B8: 45675 | C8: C107 | D8: Vinay | E8: 30 | F8: Male | G8: Pune | H8: Maharashtra | I8: New | J8: P107 | K8: Furniture | L8: Table | M8: 2 | N8: 8000 | O8: 7 | P8: Card | Q8: Delivered | R8: 14880 | S8: 11000 | T8: 3880 | V8: =IF(E8<=25,"18-25", IF(E8<=35,"26-35", IF(E8<=45,"36-45","46+"))) -> 26-35
A9: ORD008 | B9: 45679 | C9: C108 | D9: Divya | E9: 26 | F9: Female | G9: Hyderabad | H9: Telangana | I9: New | J9: P108 | K9: Mobile | L9: Headphones | M9: 3 | N9: 4000 | O9: 5 | P9: UPI | Q9: Cancelled | R9: 11400 | S9: 8000 | T9: 3400 | V9: =IF(E9<=25,"18-25", IF(E9<=35,"26-35", IF(E9<=45,"36-45","46+"))) -> 26-35
A10: ORD009 | B10: 45682 | C10: C109 | D10: Ravi | E10: 45 | F10: Male | G10: Chennai | H10: Tamil Nadu | I10: Returning | J10: P109 | K10: Electronics | L10: Monitor | M10: 2 | N10: 12000 | O10: 10 | P10: Card | Q10: Delivered | R10: 21600 | S10: 16000 | T10: 5600 | V10: =IF(E10<=25,"18-25", IF(E10<=35,"26-35", IF(E10<=45,"36-45","46+"))) -> 36-45
A11: ORD010 | B11: 45685 | C11: C110 | D11: Latha | E11: 38 | F11: Female | G11: Vijayawada | H11: Andhra Pradesh | I11: New | J11: P110 | K11: Clothing | L11: Shoes | M11: 2 | N11: 5000 | O11: 15 | P11: Cash | Q11: Delivered | R11: 8500 | S11: 6000 | T11: 2500 | V11: =IF(E11<=25,"18-25", IF(E11<=35,"26-35", IF(E11<=45,"36-45","46+"))) -> 36-45
A12: ORD011 | B12: 45729 | C12: C125 | D12: Manish | E12: 33 | F12: Male | G12: Bangalore | H12: Karnataka | I12: New | J12: P148 | K12: Electronics | L12: Laptop | M12: 4 | N12: 55000 | O12: 0 | P12: UPI | Q12: Delivered | R12: 220000 | S12: 168000 | T12: 52000 | V12: =IF(E12<=25,"18-25", IF(E12<=35,"26-35", IF(E12<=45,"36-45","46+"))) -> 26-35
A13: ORD012 | B13: 45702 | C13: C140 | D13: Vijay | E13: 30 | F13: Male | G13: Kochi | H13: Kerala | I13: Returning | J13: P148 | K13: Furniture | L13: Desk Lamp | M13: 3 | N13: 1500 | O13: 0 | P13: Card | Q13: Pending | R13: 4500 | S13: 2700 | T13: 1800 | V13: =IF(E13<=25,"18-25", IF(E13<=35,"26-35", IF(E13<=45,"36-45","46+"))) -> 26-35
A14: ORD013 | B14: 45710 | C14: C146 | D14: Suresh | E14: 39 | F14: Male | G14: Vijayawada | H14: Andhra Pradesh | I14: New | J14: P133 | K14: Clothing | L14: Shirt | M14: 3 | N14: 1800 | O14: 15 | P14: Cash | Q14: Delivered | R14: 4590 | S14: 3000 | T14: 1590 | V14: =IF(E14<=25,"18-25", IF(E14<=35,"26-35", IF(E14<=45,"36-45","46+"))) -> 36-45
A15: ORD014 | B15: 45735 | C15: C169 | D15: Deepak | E15: 23 | F15: Male | G15: Ahmedabad | H15: Gujarat | I15: Returning | J15: P147 | K15: Beauty | L15: Makeup Kit | M15: 2 | N15: 2500 | O15: 0 | P15: UPI | Q15: Delivered | R15: 5000 | S15: 3200 | T15: 1800 | V15: =IF(E15<=25,"18-25", IF(E15<=35,"26-35", IF(E15<=45,"36-45","46+"))) -> 18-25
A16: ORD015 | B16: 45738 | C16: C148 | D16: Suresh | E16: 24 | F16: Male | G16: Pune | H16: Maharashtra | I16: Returning | J16: P121 | K16: Clothing | L16: Jeans | M16: 3 | N16: 2500 | O16: 10 | P16: Card | Q16: Delivered | R16: 6750 | S16: 4500 | T16: 2250 | V16: =IF(E16<=25,"18-25", IF(E16<=35,"26-35", IF(E16<=45,"36-45","46+"))) -> 18-25
A17: ORD016 | B17: 45733 | C17: C198 | D17: Alok | E17: 58 | F17: Male | G17: Chennai | H17: Tamil Nadu | I17: New | J17: P135 | K17: Furniture | L17: Desk Lamp | M17: 3 | N17: 1500 | O17: 15 | P17: Card | Q17: Delivered | R17: 3825 | S17: 2700 | T17: 1125 | V17: =IF(E17<=25,"18-25", IF(E17<=35,"26-35", IF(E17<=45,"36-45","46+"))) -> 46+
... A111: ORD110 | B111: 45698 | C111: C192 | D111: Rohan | E111: 51 | F111: Male | G111: Bangalore | H111: Karnataka | I111: Returning | J111: P132 | K111: Clothing | L111: Jacket | M111: 2 | N111: 4000 | O111: 10 | P111: Cash | Q111: Delivered | R111: 7200 | S111: 5200 | T111: 2000 | V111: =IF(E111<=25,"18-25", IF(E111<=35,"26-35", IF(E111<=45,"36-45","46+"))) -> 46+

Sheet Pivot_Category
A3: Row Labels | B3: Sales Details
A4: Beauty | B4: 147845
A5: Clothing | B5: 198834
A6: Electronics | B6: 1356150
A7: Furniture | B7: 263430
A8: Mobile | B8: 720300
A9: Grand Total | B9: 2686559

Sheet Pivot_City
A3: Row Labels | B3: Sales Details | F3: Ahmedabad | G3: 15170
A4: Ahmedabad | B4: 15170 | F4: Bangalore | G4: 86086
A5: Bangalore | B5: 86086 | F5: Chennai | G5: 68210
A6: Chennai | B6: 68210 | F6: Delhi | G6: 25900
A7: Delhi | B7: 25900 | F7: Hyderabad | G7: 21996
A8: Hyderabad | B8: 21996 | F8: Jaipur | G8: 84680
A9: Jaipur | B9: 84680 | F9: Kochi | G9: 44092
A10: Kochi | B10: 44092 | F10: Kolkata | G10: 39150
A11: Kolkata | B11: 39150 | F11: Lucknow | G11: 47780
A12: Lucknow | B12: 47780 | F12: Mumbai | G12: 24510
A13: Mumbai | B13: 24510 | F13: Pune | G13: 49580
A14: Pune | B14: 49580 | F14: Vijayawada | G14: 54705
A15: Vijayawada | B15: 54705 | F15: Visakhapatnam | G15: 87600
A16: Visakhapatnam | B16: 87600
A17: Grand Total | B17: 649459

Sheet Pivot_Date
A3: Row Labels | B3: Sum of Sales_Amount
A4: Jan | B4: 209105
A5: Feb | B5: 1266948
A6: Mar | B6: 1210506
A7: Grand Total | B7: 2686559

Sheet Pivot_Customer
A3: Row Labels | B3: Sales Details
A4: New | B4: 1215506
A5: Returning | B5: 1471053
A6: Grand Total | B6: 2686559

Sheet Analysis
A1: Sales Dashboard Analysis
A3: Total Sales | B3: =SUM(Cleaned_Data!R:R) -> 2686559
A4: Total Profit | B4: =SUM(Cleaned_Data!T:T) -> 649459
A5: Total Orders | B5: =COUNTA(Cleaned_Data!A:A)-1 -> 110
A6: Average Sales | B6: =AVERAGE(Cleaned_Data!R:R) -> 24423.264
